flax_gate_loop/__init__.py
flax_gate_loop/gate_loop.py
flax_gate_loop/transformer.py
flax_gate_loop/base_models/__init__.py
flax_gate_loop/base_models/channel_mixing.py
flax_gate_loop/base_models/language_model.py
flax_gate_loop/base_models/sequence_model.py
flax_gate_loop/base_models/time_mixing.py
flax_gate_loop/language_models/__init__.py
flax_gate_loop/language_models/gate_loop_lm.py
flax_gate_loop/language_models/transformer_lm.py
flax_gate_loop-1.0.3.dist-info/LICENSE.txt
flax_gate_loop-1.0.3.dist-info/METADATA
flax_gate_loop-1.0.3.dist-info/WHEEL
flax_gate_loop-1.0.3.dist-info/top_level.txt
flax_gate_loop-1.0.3.dist-info/RECORD
