Metadata-Version: 2.1
Name: flax-gate-loop
Version: 1.0.3
Summary: GateLoop Model
Home-page: https://github.com/tobiaskatsch/GateLoop
Author: Tobias Katsch
Author-email: tobias.katsch42@gmail.com
License: Apache License, Version 2.0
Requires-Python: >=3.7
License-File: LICENSE.txt
Requires-Dist: jax >=0.4.20
Requires-Dist: flax >=0.8.0
